{"version":1,"resource":"file:///home/river/.config/waybar/config.jsonc","entries":[{"id":"ATRd.jsonc","timestamp":1768552768171},{"id":"A5Va.jsonc","timestamp":1768552977246},{"id":"yQOI.jsonc","timestamp":1768553449604},{"id":"jIS4.jsonc","timestamp":1768562667113},{"id":"J2Uz.jsonc","timestamp":1768562747058},{"id":"1gRt.jsonc","timestamp":1768562773308},{"id":"WeNc.jsonc","timestamp":1768562797965},{"id":"nrCQ.jsonc","timestamp":1768562840051},{"id":"cpMd.jsonc","timestamp":1768621048184},{"id":"nCQE.jsonc","timestamp":1768676301303},{"id":"SN4Y.jsonc","timestamp":1768676376470},{"id":"Jf1c.jsonc","timestamp":1768676432374},{"id":"4fkT.jsonc","timestamp":1768676691289},{"id":"CLx2.jsonc","timestamp":1768677997721},{"id":"jHmt.jsonc","timestamp":1768678018431},{"id":"A90D.jsonc","timestamp":1768679100356},{"id":"9pjd.jsonc","timestamp":1768679152571},{"id":"Mhjj.jsonc","timestamp":1768772146476},{"id":"HRA3.jsonc","timestamp":1768806881281},{"id":"9qSq.jsonc","timestamp":1769032155502},{"id":"TdIw.jsonc","timestamp":1769032213111},{"id":"hKWG.jsonc","timestamp":1769032947108},{"id":"G4yF.jsonc","timestamp":1769033356302},{"id":"OTIY.jsonc","timestamp":1769033549115},{"id":"Q9hC.jsonc","timestamp":1769033614507},{"id":"KZVv.jsonc","timestamp":1769033866590},{"id":"lHyf.jsonc","source":"undoRedo.source","timestamp":1769033920228},{"id":"Lc8w.jsonc","timestamp":1769033962069},{"id":"fK3E.jsonc","timestamp":1769034153352},{"id":"7BQ2.jsonc","timestamp":1769034176270},{"id":"ijxH.jsonc","timestamp":1769034220745},{"id":"UdWL.jsonc","timestamp":1769034273303},{"id":"9H8n.jsonc","timestamp":1769035034276},{"id":"B1TZ.jsonc","timestamp":1769035434523},{"id":"Kj7P.jsonc","source":"undoRedo.source","timestamp":1769035474866},{"id":"1AN8.jsonc","timestamp":1769035481552},{"id":"bDl1.jsonc","timestamp":1769035528076},{"id":"EFrK.jsonc","timestamp":1769035661633},{"id":"NIGj.jsonc","timestamp":1769036172054},{"id":"KOOY.jsonc","timestamp":1769036191558},{"id":"r43W.jsonc","timestamp":1769036300948},{"id":"xrMs.jsonc","timestamp":1769036369212},{"id":"oJ5L.jsonc","timestamp":1769048371044},{"id":"aaP5.jsonc","timestamp":1769048404693}]}